{
	"configurations" : 
	[
		{
			"directories" : 
			[
				{
					"build" : ".",
					"jsonFile" : "directory-.-Debug-f5ebdc15457944623624.json",
					"minimumCMakeVersion" : 
					{
						"string" : "3.31"
					},
					"projectIndex" : 0,
					"source" : ".",
					"targetIndexes" : 
					[
						0
					]
				}
			],
			"name" : "Debug",
			"projects" : 
			[
				{
					"directoryIndexes" : 
					[
						0
					],
					"name" : "aLogger",
					"targetIndexes" : 
					[
						0
					]
				}
			],
			"targets" : 
			[
				{
					"directoryIndex" : 0,
					"id" : "aLogger::@6890427a1f51a3e7e1df",
					"jsonFile" : "target-aLogger-Debug-3f27c9b5523682fdd9c4.json",
					"name" : "aLogger",
					"projectIndex" : 0
				}
			]
		}
	],
	"kind" : "codemodel",
	"paths" : 
	{
		"build" : "/home/benjo/Desktop/Projects/aLogger/cmake-build-debug",
		"source" : "/home/benjo/Desktop/Projects/aLogger"
	},
	"version" : 
	{
		"major" : 2,
		"minor" : 7
	}
}
